{"web":{
    "client_id":"432831170698-5p7t7ffnh1u65ubkeru4mr8jvpl7uupv.apps.googleusercontent.com",
    "project_id":"secrets-417416","auth_uri":"https://accounts.google.com/o/oauth2/auth",
    "token_uri":"https://oauth2.googleapis.com/token",
    "auth_provider_x509_cert_url":"https://www.googleapis.com/oauth2/v1/certs",
    "client_secret":"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",
    "redirect_uris":["http://localhost:3030/auth/google/secrets"],
    "javascript_origins":["http://localhost:3030"]
    }}